redrover_api/__init__.py
redrover_api/api_client.py
redrover_api/api_response.py
redrover_api/configuration.py
redrover_api/exceptions.py
redrover_api/py.typed
redrover_api/rest.py
redrover_api/api/__init__.py
redrover_api/api/absence_api.py
redrover_api/api/absence_reason_api.py
redrover_api/api/absence_reason_balance_api.py
redrover_api/api/accounting_code_api.py
redrover_api/api/application_template_api.py
redrover_api/api/assignment_api.py
redrover_api/api/attribute_api.py
redrover_api/api/connection_api.py
redrover_api/api/contract_api.py
redrover_api/api/custom_fields_api.py
redrover_api/api/job_posting_api.py
redrover_api/api/job_posting_category_api.py
redrover_api/api/location_api.py
redrover_api/api/new_hire_api.py
redrover_api/api/organization_api.py
redrover_api/api/pay_code_api.py
redrover_api/api/position_type_api.py
redrover_api/api/user_api.py
redrover_api/api/vacancy_api.py
redrover_api/api/webhooks_api.py
redrover_api/models/__init__.py
redrover_api/models/absence_create_request.py
redrover_api/models/absence_detail_create_request.py
redrover_api/models/absence_detail_response.py
redrover_api/models/absence_file_attachment_response.py
redrover_api/models/absence_planned_hours_position_details.py
redrover_api/models/absence_reason_balance_create_request.py
redrover_api/models/absence_reason_balance_response.py
redrover_api/models/absence_reason_balance_update_request.py
redrover_api/models/absence_reason_category_response.py
redrover_api/models/absence_reason_response.py
redrover_api/models/absence_reason_tracking_type_enum.py
redrover_api/models/absence_reason_usage_create_request.py
redrover_api/models/absence_reason_usage_response.py
redrover_api/models/absence_response.py
redrover_api/models/absence_update_request.py
redrover_api/models/absence_vacancy_detail_request.py
redrover_api/models/absence_vacancy_request.py
redrover_api/models/access_control_request.py
redrover_api/models/access_control_response.py
redrover_api-1.15.3.dist-info/licenses/LICENSE
redrover_api-1.15.3.dist-info/METADATA
redrover_api-1.15.3.dist-info/WHEEL
redrover_api-1.15.3.dist-info/top_level.txt
redrover_api-1.15.3.dist-info/RECORD
