Metadata-Version: 2.4
Name: redrover-api
Version: 1.15.3
Summary: Red Rover API
Home-page: https://github.com/edustaff/redrover-api
Author: Integrations
Author-email: integrations@redroverk12.com
Keywords: OpenAPI,OpenAPI-Generator,Red Rover API
License-File: LICENSE
Requires-Dist: urllib3<2.1.0,>=1.25.3
Requires-Dist: python-dateutil
Requires-Dist: pydantic>=2
Requires-Dist: typing-extensions>=4.7.1
Dynamic: author
Dynamic: author-email
Dynamic: description
Dynamic: description-content-type
Dynamic: home-page
Dynamic: keywords
Dynamic: license-file
Dynamic: requires-dist
Dynamic: summary
